glip_object_detection.libs/libcudart-80664282.so.10.2.89
glip_object_detection-0.1.0.dist-info/RECORD
glip_object_detection-0.1.0.dist-info/top_level.txt
glip_object_detection-0.1.0.dist-info/METADATA
glip_object_detection-0.1.0.dist-info/WHEEL
glip/_C.cpython-39-x86_64-linux-gnu.so
glip/__init__.py
glip/structures/__init__.py
glip/structures/image_list.py
glip/structures/bounding_box.py
glip/structures/boxlist_ops.py
glip/structures/keypoint.py
glip/config/defaults.py
glip/config/__init__.py
glip/config/paths_catalog.py
glip/layers/roi_pool.py
glip/layers/dyrelu.py
glip/layers/dropblock.py
glip/layers/sigmoid_focal_loss.py
glip/layers/roi_align.py
glip/layers/se.py
glip/layers/__init__.py
glip/layers/evonorm.py
glip/layers/smooth_l1_loss.py
glip/layers/nms.py
glip/layers/batch_norm.py
glip/layers/misc.py
glip/layers/set_loss.py
glip/layers/iou_loss.py
glip/layers/deform_pool.py
glip/layers/dyhead.py
glip/layers/deform_conv.py
glip/modeling/box_coder.py
glip/modeling/utils.py
glip/modeling/__init__.py
glip/modeling/matcher.py
glip/modeling/make_layers.py
glip/modeling/poolers.py
glip/modeling/registry.py
glip/modeling/balanced_positive_negative_sampler.py
glip/modeling/language_backbone/simple_tokenizer.py
glip/modeling/language_backbone/build.py
glip/modeling/language_backbone/bert_model.py
glip/modeling/language_backbone/__init__.py
glip/modeling/language_backbone/test_clip_tokenizer.py
glip/modeling/language_backbone/clip_model.py
glip/modeling/language_backbone/hfpt_tokenizer.py
glip/modeling/language_backbone/backbone.py
glip/modeling/language_backbone/word_utils.py
glip/modeling/language_backbone/rnn_model.py
glip/modeling/rpn/retina.py
glip/modeling/rpn/rpn.py
glip/modeling/rpn/inference.py
glip/modeling/rpn/__init__.py
glip/modeling/rpn/atss.py
glip/modeling/rpn/vldyhead.py
glip/modeling/rpn/fcos.py
glip/modeling/rpn/modeling_bert.py
glip/modeling/rpn/transformer.py
glip/modeling/rpn/dyhead.py
glip/modeling/rpn/anchor_generator.py
glip/modeling/roi_heads/__init__.py
glip/modeling/roi_heads/box_head/loss.py
glip/modeling/roi_heads/box_head/roi_box_predictors.py
